pysyte/__init__.py
pysyte/args.py
pysyte/code.py
pysyte/darwin.py
pysyte/debuggers.py
pysyte/decorators.py
pysyte/dictionaries.py
pysyte/dictionaries.test
pysyte/getch.py
pysyte/imports.py
pysyte/iteration.py
pysyte/keyboard.py
pysyte/linux.py
pysyte/lists.py
pysyte/literals.py
pysyte/paths.py
pysyte/paths.test
pysyte/platforms.py
pysyte/pp.py
pysyte/randoms.py
pysyte/scripts.py
pysyte/splits.py
pysyte/splits.test
pysyte/streams.py
pysyte/streams.test
pysyte/term.py
pysyte/text_streams.py
pysyte/tracebacks.py
pysyte/words.py
pysyte/words.test
pysyte/words.tests
pysyte/bash/__init__.py
pysyte/bash/cmnds.py
pysyte/bash/git.py
pysyte/bash/git.test
pysyte/bash/shell.py
pysyte/colours/__init__.py
pysyte/colours/ansi_escapes.py
pysyte/colours/ansi_escapes.test
pysyte/colours/colour_names.py
pysyte/colours/colour_names.test
pysyte/colours/colour_numbers.py
pysyte/colours/colour_numbers.test
pysyte/colours/colour_numbers.tests
pysyte/colours/main.py
pysyte/colours/texts.py
pysyte/colours/texts.test
pysyte/colours/texts.tests
pysyte/colours/x11_colour_names.py
pysyte/colours/x11_colour_names.test
pysyte/testing/__init__.py
pysyte/testing/files_for_test.py
pysyte/testing/files_for_test.test
pysyte/testing/files_for_test.tests
pysyte/testing/see.py
pysyte/testing/see.test
pysyte/testing/see.tests
pysyte/testing/try_plugins.py
pysyte/testing/try_plugins.test
pysyte/testing/trying.py
pysyte/testing/trying.test
pysyte-0.7.11.data/scripts/kat
pysyte-0.7.11.data/scripts/short_dir
pysyte-0.7.11.data/scripts/try
pysyte-0.7.11.dist-info/LICENSE
pysyte-0.7.11.dist-info/METADATA
pysyte-0.7.11.dist-info/WHEEL
pysyte-0.7.11.dist-info/top_level.txt
pysyte-0.7.11.dist-info/RECORD
