Metadata-Version: 2.1
Name: pysyte
Version: 0.7.11
Summary: Python modules often used in dotjab, and elsewhere
Home-page: https://github.com/jalanb/pysyte
Author: J Alan Brogan
Author-email: github@al-got-rhythm.net
License: MIT License
Download-URL: https://github.com/jalanb/pysyte/tarball/v0.7.11
Platform: any
Classifier: Programming Language :: Python :: 3.7
Classifier: Development Status :: 3 - Alpha
Classifier: Natural Language :: English
Classifier: Environment :: Console
Classifier: Intended Audience :: Developers
Classifier: License :: OSI Approved :: MIT License
Classifier: Operating System :: OS Independent
Classifier: Topic :: Software Development :: Build Tools
Requires-Dist: inflect
Requires-Dist: pprintpp
Requires-Dist: path.py (==7.7.1)
Requires-Dist: six
Provides-Extra: testing
Requires-Dist: nose ; extra == 'testing'
